rust_arenaclient-0.2.4.dist-info/METADATA
rust_arenaclient-0.2.4.dist-info/WHEEL
rust_ac/bot.py
rust_ac/game_config.py
rust_ac/match_runner.py
rust_ac/requirements.txt
rust_ac/result.py
rust_ac/server.py
rust_ac/supervisor.py
rust_ac/__init__.py
rust_ac/__main__.py
rust_ac/rust_ac.cp39-win_amd64.pyd
rust_arenaclient-0.2.4.dist-info/RECORD
