Metadata-Version: 2.1
Name: rust-arenaclient
Version: 0.2.4
Requires-Dist: portpicker
Requires-Dist: aiohttp
Author: Daniel <danielvanschoor1997@gmail.com>
Author-email: Daniel <danielvanschoor1997@gmail.com>
